OnClass/BilinearNN.py
OnClass/OnClassModel.py
OnClass/OnClass_utils.py
OnClass/__init__.py
OnClass-1.3.dist-info/LICENSE
OnClass-1.3.dist-info/METADATA
OnClass-1.3.dist-info/WHEEL
OnClass-1.3.dist-info/top_level.txt
OnClass-1.3.dist-info/RECORD
