Metadata-Version: 2.1
Name: OnClass
Version: 1.3
Summary: Single Cell Annotation based on the Cell Ontology
Home-page: https://github.com/wangshenguiuc/OnClass
Author: Sheng Wang
Author-email: swang91@uw.edu
License: MIT Licence
Keywords: pip,single cell,OnClass
Platform: any
License-File: LICENSE
Requires-Dist: sentence-transformers
Requires-Dist: anndata >=0.6.4
Requires-Dist: fbpca >=1.0
Requires-Dist: umap-learn >=0.3.10
Requires-Dist: matplotlib >=2.0.2
Requires-Dist: numpy >=1.16.4
Requires-Dist: scipy >=1.3.1
Requires-Dist: scikit-learn >=0.21.3
Requires-Dist: scanorama >=1.7.1
